bepatient/__init__.py
bepatient/api.py
bepatient/curler.py
bepatient/py.typed
bepatient/retry.py
bepatient/waiter_src/__init__.py
bepatient/waiter_src/comparators.py
bepatient/waiter_src/conditions_manager.py
bepatient/waiter_src/exceptions.py
bepatient/waiter_src/waiter.py
bepatient/waiter_src/checkers/__init__.py
bepatient/waiter_src/checkers/checker.py
bepatient/waiter_src/checkers/response_checkers.py
bepatient/waiter_src/executors/__init__.py
bepatient/waiter_src/executors/executor.py
bepatient/waiter_src/executors/requests_executor.py
bepatient-0.17.0.dist-info/LICENSE
bepatient-0.17.0.dist-info/METADATA
bepatient-0.17.0.dist-info/WHEEL
bepatient-0.17.0.dist-info/top_level.txt
bepatient-0.17.0.dist-info/RECORD
