Metadata-Version: 2.2
Name: bepatient
Version: 0.17.0
Summary: A library facilitating work with asynchronous APIs
Author-email: Dawid Szaniawski <dszaniawski@webludus.pl>
License: MIT License
Project-URL: Homepage, https://webludus.pl/en
Project-URL: Source, https://github.com/dawid-szaniawski/bepatient
Project-URL: Documentation, https://bepatient.webludus.pl/
Keywords: api,async,api_testing,automation,json,testing,web
Classifier: Development Status :: 4 - Beta
Classifier: Environment :: Web Environment
Classifier: Intended Audience :: Developers
Classifier: Natural Language :: English
Classifier: Operating System :: OS Independent
Classifier: License :: OSI Approved :: MIT License
Classifier: Programming Language :: Python
Classifier: Programming Language :: Python :: 3.10
Classifier: Programming Language :: Python :: 3.11
Classifier: Programming Language :: Python :: 3.12
Classifier: Programming Language :: Python :: 3.13
Classifier: Programming Language :: Python :: 3 :: Only
Classifier: Programming Language :: Python :: Implementation :: CPython
Classifier: Topic :: Internet :: WWW/HTTP
Classifier: Topic :: Software Development :: Libraries
Classifier: Topic :: Software Development :: Testing
Classifier: Topic :: Software Development :: Quality Assurance
Classifier: Topic :: Utilities
Classifier: Topic :: File Formats :: JSON
Classifier: Topic :: File Formats :: JSON :: JSON Schema
Classifier: Typing :: Typed
Requires-Python: >=3.10
License-File: LICENSE
Requires-Dist: dictor>=0.1.12
Requires-Dist: requests>=2.28.1
Provides-Extra: dev
Requires-Dist: black>=24.10.0; extra == "dev"
Requires-Dist: flake8>=7.1.1; extra == "dev"
Requires-Dist: isort>=5.13.2; extra == "dev"
Requires-Dist: mypy>=1.14.1; extra == "dev"
Requires-Dist: pylint>=3.3.3; extra == "dev"
Requires-Dist: pytest>=8.3.4; extra == "dev"
Requires-Dist: pytest-cov>=5.0.0; extra == "dev"
Requires-Dist: pytest-mock>=3.14.0; extra == "dev"
Requires-Dist: responses>=0.25.6; extra == "dev"
Requires-Dist: ruff>=0.9.2; extra == "dev"
Requires-Dist: tox>=4.23.2; extra == "dev"
Requires-Dist: twine>=6.0.1; extra == "dev"
Provides-Extra: docs
Requires-Dist: mkdocs-material>=9.5.50; extra == "docs"
Requires-Dist: mkdocs-minify-plugin>=0.8.0; extra == "docs"
